Bidirectional_Hash_Map/__init__.py
Bidirectional_Hash_Map/bidirectional_hash_map.py
Bidirectional_Hash_Map-1.0.dist-info/LICENSE
Bidirectional_Hash_Map-1.0.dist-info/METADATA
Bidirectional_Hash_Map-1.0.dist-info/WHEEL
Bidirectional_Hash_Map-1.0.dist-info/entry_points.txt
Bidirectional_Hash_Map-1.0.dist-info/top_level.txt
Bidirectional_Hash_Map-1.0.dist-info/RECORD
