Metadata-Version: 2.1
Name: Bidirectional-Hash-Map
Version: 1.0
Summary: This package contains implementation of a bidirectional hash map.
Home-page: https://github.com/DtjiAppDev/BIDIRECTIONAL_HASH_MAP
Author: Dtji AppDev
Author-email: dtjiappdev1999@gmail.com
License: MIT
Platform: UNKNOWN
Classifier: Programming Language :: Python :: 3
Classifier: Programming Language :: Python :: 3.7
